tensorrt/__init__.pyi
tensorrt_bindings/__init__.pyi
tensorrt_bindings/tensorrt.pyi
tensorrt_stubs/__init__.py
tensorrt_stubs/py.typed
tensorrt_stubs-10.13.0.35.1.dist-info/METADATA
tensorrt_stubs-10.13.0.35.1.dist-info/WHEEL
tensorrt_stubs-10.13.0.35.1.dist-info/licenses/LICENSE
tensorrt_stubs-10.13.0.35.1.dist-info/RECORD
