Metadata-Version: 2.4
Name: tensorrt-stubs
Version: 10.13.0.35.1
Summary: Type stubs for NVIDIA TensorRT
Project-URL: Homepage, https://github.com/sync-dev-org/tensorrt-stubs
Author-email: minamik <mia@sync.dev>
License: MIT License
License-File: LICENSE
Classifier: Development Status :: 4 - Beta
Classifier: Intended Audience :: Developers
Classifier: License :: OSI Approved :: MIT License
Classifier: Programming Language :: Python :: 3
Classifier: Programming Language :: Python :: 3.10
Classifier: Programming Language :: Python :: 3.11
Classifier: Programming Language :: Python :: 3.12
Classifier: Programming Language :: Python :: 3.13
Classifier: Typing :: Stubs Only
Requires-Python: >=3.10
Requires-Dist: numpy
Requires-Dist: tensorrt-cu12-bindings==10.13.0.35
Requires-Dist: tensorrt==10.13.0.35
Provides-Extra: dev
Requires-Dist: black>=23.7.0; extra == 'dev'
Requires-Dist: flake8>=6.1.0; extra == 'dev'
Requires-Dist: pybind11-stubgen>=2.5.4; extra == 'dev'
Requires-Dist: pytest>=8.3.5; extra == 'dev'
Requires-Dist: twine>=6.1.0; extra == 'dev'
